UbLite/__init__.py
UbLite/config.py
UbLite/fwd.py
UbLite/gif.py
UbLite/help.py
UbLite/js.py
UbLite/purge.py
UbLite/sdm.py
UbLite/setup_config.py
UbLite/spam.py
UbLite/stickers.py
UbLite/translate.py
UbLite/update.py
UbLite/userbot.py
ublite-0.1.0.dist-info/licenses/LICENSE
ublite-0.1.0.dist-info/METADATA
ublite-0.1.0.dist-info/WHEEL
ublite-0.1.0.dist-info/entry_points.txt
ublite-0.1.0.dist-info/top_level.txt
ublite-0.1.0.dist-info/RECORD
