Metadata-Version: 2.4
Name: UbLite
Version: 0.1.0
Summary: A lightweight and efficient Telegram userbot for automation.
Home-page: https://github.com/ankit-chaubey/UbLite
Author: Ankit Chaubey
Author-email: m.ankitchaubey@gmail.com
Classifier: Programming Language :: Python :: 3
Classifier: License :: OSI Approved :: MIT License
Classifier: Operating System :: OS Independent
Requires-Python: >=3.10
License-File: LICENSE
Requires-Dist: telethon
Requires-Dist: colorama
Dynamic: author
Dynamic: author-email
Dynamic: classifier
Dynamic: description
Dynamic: description-content-type
Dynamic: home-page
Dynamic: license-file
Dynamic: requires-dist
Dynamic: requires-python
Dynamic: summary
